frankik-1.0.0.dist-info/RECORD
frankik-1.0.0.dist-info/WHEEL
frankik-1.0.0.dist-info/METADATA
frankik-1.0.0.dist-info/licenses/LICENSE
frankik/_core.pyi
frankik/__init__.py
frankik/_core.cpython-311-darwin.so
