Metadata-Version: 2.4
Name: frankik
Version: 1.0.0
Summary: Standalone blazing fast, analytical inverse kinematics for Franka Panda and FR3 robots.
Author-Email: =?utf-8?q?Tobias_J=C3=BClg?= <tobias@juelg.net>
Maintainer-Email: =?utf-8?q?Tobias_J=C3=BClg?= <tobias@juelg.net>
License-Expression: MIT
Classifier: Programming Language :: Python :: 3
Project-URL: Homepage, https://github.com/juelg/frankik
Project-URL: Issues, https://github.com/juelg/frankik/issues
Requires-Python: >=3.10
Requires-Dist: numpy
Provides-Extra: dev
Requires-Dist: ruff==0.3.2; extra == "dev"
Requires-Dist: black==24.1.1; extra == "dev"
Requires-Dist: isort==5.13.2; extra == "dev"
Requires-Dist: mypy==1.10.1; extra == "dev"
Requires-Dist: types-requests~=2.31; extra == "dev"
Requires-Dist: pybind11-stubgen==2.5.5; extra == "dev"
Requires-Dist: pytest==8.1.1; extra == "dev"
Requires-Dist: commitizen~=3.28.0; extra == "dev"
Requires-Dist: clang; extra == "dev"
Requires-Dist: clang-format; extra == "dev"
Requires-Dist: clang-tidy; extra == "dev"
Requires-Dist: scipy; extra == "dev"
